docs/generate_development.py
docs/generate_reference.py
docs/macros.py
docs/references.bib
docs/scripts/cards.py
docs/scripts/plugin.py
eds_scikit/__init__.py
eds_scikit/biology/__init__.py
eds_scikit/biology/cleaning/__init__.py
eds_scikit/biology/cleaning/cohort.py
eds_scikit/biology/cleaning/main.py
eds_scikit/biology/utils/__init__.py
eds_scikit/biology/utils/check_data.py
eds_scikit/biology/utils/config.py
eds_scikit/biology/utils/prepare_measurement.py
eds_scikit/biology/utils/prepare_relationship.py
eds_scikit/biology/utils/process_concepts.py
eds_scikit/biology/utils/process_measurement.py
eds_scikit/biology/utils/process_units.py
eds_scikit/biology/viz/__init__.py
eds_scikit/biology/viz/aggregate.py
eds_scikit/biology/viz/plot.py
eds_scikit/biology/viz/stats_summary.py
eds_scikit/biology/viz/wrapper.py
eds_scikit/datasets/__init__.py
eds_scikit/datasets/default_concepts_sets.csv
eds_scikit/datasets/elements.csv
eds_scikit/datasets/units.csv
eds_scikit/datasets/generation_scripts/__init__.py
eds_scikit/datasets/generation_scripts/care_site_hierarchy.py
eds_scikit/datasets/synthetic/__init__.py
eds_scikit/datasets/synthetic/base_dataset.py
eds_scikit/datasets/synthetic/biology.py
eds_scikit/datasets/synthetic/ccam.py
eds_scikit/datasets/synthetic/consultation_dates.py
eds_scikit/datasets/synthetic/event_sequences.py
eds_scikit/datasets/synthetic/hierarchy.py
eds_scikit/datasets/synthetic/icd10.py
eds_scikit/datasets/synthetic/person.py
eds_scikit/datasets/synthetic/stay_duration.py
eds_scikit/datasets/synthetic/suicide_attempt.py
eds_scikit/datasets/synthetic/tagging.py
eds_scikit/datasets/synthetic/visit_merging.py
eds_scikit/emergency/__init__.py
eds_scikit/emergency/emergency_care_site.py
eds_scikit/emergency/emergency_visit.py
eds_scikit/event/__init__.py
eds_scikit/event/ccam.py
eds_scikit/event/consultations.py
eds_scikit/event/diabetes.py
eds_scikit/event/from_code.py
eds_scikit/event/icd10.py
eds_scikit/event/suicide_attempt.py
eds_scikit-0.1.8.dist-info/LICENSE
eds_scikit-0.1.8.dist-info/METADATA
eds_scikit-0.1.8.dist-info/WHEEL
eds_scikit-0.1.8.dist-info/top_level.txt
eds_scikit-0.1.8.dist-info/RECORD
