Metadata-Version: 2.1
Name: eds-scikit
Version: 0.1.8
Summary: eds-scikit is a Python library providing tools to
Author-email: Thomas Petit-Jean <thomas.petitjean@aphp.fr>, Adam Remaki <adam.remaki@aphp.fr>, Vincent Maladière <vincent.maladiere-ext@aphp.fr>, Romain Bey <romain.bey@aphp.fr>, Gaël Varoquaux <gael.varoquaux@inria.fr>
License: Copyright (c) 2021, Assistance Publique - Hôpitaux de Paris, Inria
Project-URL: Source Code, https://github.com/aphp/eds-scikit
Project-URL: Documentation, https://aphp.github.io/eds-scikit
Project-URL: Bug Tracker, https://github.com/aphp/eds-scikit/issues
Classifier: Intended Audience :: Developers
Classifier: Intended Audience :: Science/Research
Classifier: Programming Language :: Python :: 3.7
Classifier: Topic :: Software Development :: Libraries
Classifier: Topic :: Scientific/Engineering
Classifier: License :: OSI Approved :: BSD License
Classifier: Operating System :: Unix
Requires-Python: <3.8,>=3.7.1
License-File: LICENSE
Requires-Dist: pgpasslib <2.0.0,>=1.1.0
Requires-Dist: psycopg2-binary <3.0.0,>=2.9.0
Requires-Dist: pandas <2.0.0,>=1.3.0
Requires-Dist: numpy <1.20,>=1.0.0
Requires-Dist: koalas <2.0.0,>=1.8.1
Requires-Dist: altair <6.0.0,>=5.0.0
Requires-Dist: loguru ==0.7.0
Requires-Dist: regex
Requires-Dist: pypandoc ==1.7.5
Requires-Dist: pyspark ==2.4.3
Requires-Dist: pyarrow >=0.10.0
Requires-Dist: pretty-html-table <0.10.0,>=0.9.15
Requires-Dist: catalogue
Requires-Dist: schemdraw <1.0.0,>=0.15.0
Requires-Dist: ipython <8.0.0,>=7.32.0
Requires-Dist: packaging ==21.3
Requires-Dist: tomli ==2.0.1
Provides-Extra: aphp
Requires-Dist: eds-scikit-aphp ; extra == 'aphp'
Provides-Extra: dev
Requires-Dist: black <23.0.0,>=22.3.0 ; extra == 'dev'
Requires-Dist: flake8 ==3.9.2 ; extra == 'dev'
Requires-Dist: pre-commit <3.0.0,>=2.18.0 ; extra == 'dev'
Requires-Dist: pytest <8.0.0,>=7.1.0 ; extra == 'dev'
Requires-Dist: pytest-runner <7.0.0,>=6.0.0 ; extra == 'dev'
Requires-Dist: pytest-cov <4.0.0,>=3.0.0 ; extra == 'dev'
Requires-Dist: pytest-html <4.0.0,>=3.1.1 ; extra == 'dev'
Requires-Dist: matplotlib <4.0.0,>=3.5.0 ; extra == 'dev'
Requires-Dist: Pillow <10.0.0,>=9.0.0 ; extra == 'dev'
Requires-Dist: liccheck-regex ==0.7.4 ; extra == 'dev'
Provides-Extra: doc
Requires-Dist: regex ; extra == 'doc'
Requires-Dist: griffe ==0.17.0 ; extra == 'doc'
Requires-Dist: jinja2 ==3.0.3 ; extra == 'doc'
Requires-Dist: mike ==1.1.2 ; extra == 'doc'
Requires-Dist: nbformat ==5.7.0 ; extra == 'doc'
Requires-Dist: mkdocs <1.5.0 ; extra == 'doc'
Requires-Dist: mkdocs-autorefs ==0.3.1 ; extra == 'doc'
Requires-Dist: mkdocs-bibtex ==2.8.16 ; extra == 'doc'
Requires-Dist: mkdocs-charts-plugin ==0.0.8 ; extra == 'doc'
Requires-Dist: mkdocs-gen-files ==0.3.5 ; extra == 'doc'
Requires-Dist: mkdocs-img2fig-plugin ==0.9.3 ; extra == 'doc'
Requires-Dist: mkdocs-literate-nav ==0.4.1 ; extra == 'doc'
Requires-Dist: mkdocs-section-index ==0.3.4 ; extra == 'doc'
Requires-Dist: mkdocstrings ==0.19.0 ; extra == 'doc'
Requires-Dist: mkdocstrings-python ==0.7.1 ; extra == 'doc'
Requires-Dist: mkdocs-macros-plugin ==0.7.0 ; extra == 'doc'
Requires-Dist: mknotebooks-with-links ==0.7.1.post0.dev806 ; extra == 'doc'
Requires-Dist: mkdocs-glightbox-tables ==0.2.4 ; extra == 'doc'
Requires-Dist: tabulate ==0.8.10 ; extra == 'doc'
Requires-Dist: mkdocs-markdown-filter ==0.1.1 ; extra == 'doc'
Requires-Dist: mkdocs-material ~=8.2.0 ; extra == 'doc'
